LICENSE.md
README.md
setup.py
qqddm/__init__.py
qqddm/main.py
qqddm/utils.py
qqddm.egg-info/PKG-INFO
qqddm.egg-info/SOURCES.txt
qqddm.egg-info/dependency_links.txt
qqddm.egg-info/requires.txt
qqddm.egg-info/top_level.txt
qqddm/models/__init__.py
qqddm/models/qqddm_api.py
qqddm/models/exceptions/__init__.py
qqddm/models/exceptions/base.py
qqddm/models/exceptions/qqddm_api.py